CHANGELOG.md
LICENSE
entropylab_qpudb/__init__.py
entropylab_qpudb/_entropy_cal.py
entropylab_qpudb/_gateconcatenator.py
entropylab_qpudb/_qpudatabase.py
entropylab_qpudb/_quaconfig.py
entropylab_qpudb/_resolver.py
entropylab_qpudb-0.0.11.dist-info/LICENSE
entropylab_qpudb-0.0.11.dist-info/WHEEL
entropylab_qpudb-0.0.11.dist-info/METADATA
entropylab_qpudb-0.0.11.dist-info/RECORD
